orchestract/__init__.py
orchestract/main.py
orchestract-0.0.0.dist-info/LICENSE
orchestract-0.0.0.dist-info/METADATA
orchestract-0.0.0.dist-info/WHEEL
orchestract-0.0.0.dist-info/RECORD
